pygsielev/__init__.py
pygsielev/elevation.py
pygsielev/standard_meshcode.py
pygsielev-0.1.1.dist-info/METADATA
pygsielev-0.1.1.dist-info/WHEEL
pygsielev-0.1.1.dist-info/RECORD
