Metadata-Version: 2.1
Name: pygsielev
Version: 0.1.1
Summary: 
Author: Takeshi Sagara
Author-email: sagara@info-proto.com
Requires-Python: >=3.9,<4.0
Classifier: Programming Language :: Python :: 3
Classifier: Programming Language :: Python :: 3.9
Classifier: Programming Language :: Python :: 3.10
Classifier: Programming Language :: Python :: 3.11
Classifier: Programming Language :: Python :: 3.12
